neon_data_models/__init__.py
neon_data_models/enum.py
neon_data_models/types.py
neon_data_models/util.py
neon_data_models/version.py
neon_data_models/models/__init__.py
neon_data_models/models/api/__init__.py
neon_data_models/models/api/chatbots.py
neon_data_models/models/api/jwt.py
neon_data_models/models/api/llm.py
neon_data_models/models/api/http/__init__.py
neon_data_models/models/api/http/brainforge.py
neon_data_models/models/api/http/neon.py
neon_data_models/models/api/klat/__init__.py
neon_data_models/models/api/klat/socketio.py
neon_data_models/models/api/messagebus/__init__.py
neon_data_models/models/api/mq/__init__.py
neon_data_models/models/api/mq/brainforge.py
neon_data_models/models/api/mq/chatbots.py
neon_data_models/models/api/mq/llm.py
neon_data_models/models/api/mq/neon.py
neon_data_models/models/api/mq/users.py
neon_data_models/models/api/node_v1/__init__.py
neon_data_models/models/base/__init__.py
neon_data_models/models/base/contexts.py
neon_data_models/models/base/messagebus.py
neon_data_models/models/client/__init__.py
neon_data_models/models/client/node.py
neon_data_models/models/user/__init__.py
neon_data_models/models/user/database.py
neon_data_models/models/user/neon_profile.py
neon_data_models-0.0.2a17.dist-info/licenses/LICENSE.md
neon_data_models-0.0.2a17.dist-info/METADATA
neon_data_models-0.0.2a17.dist-info/WHEEL
neon_data_models-0.0.2a17.dist-info/top_level.txt
neon_data_models-0.0.2a17.dist-info/zip-safe
neon_data_models-0.0.2a17.dist-info/RECORD
