Metadata-Version: 2.4
Name: neon-data-models
Version: 0.0.2a17
Summary: Pydantic models and associated JSON schema definitions
Home-page: https://github.com/NeonGeckoCom/neon-data-models
Author: NeonGecko
Author-email: developers@neon.ai
License: BSD-3-Clause
Classifier: Intended Audience :: Developers
Classifier: Programming Language :: Python :: 3
License-File: LICENSE.md
Requires-Dist: pydantic~=2.9
Requires-Dist: pytz
Provides-Extra: test
Requires-Dist: pytest; extra == "test"
Requires-Dist: ovos-bus-client~=0.1; extra == "test"
Dynamic: author
Dynamic: author-email
Dynamic: classifier
Dynamic: description
Dynamic: description-content-type
Dynamic: home-page
Dynamic: license
Dynamic: license-file
Dynamic: provides-extra
Dynamic: requires-dist
Dynamic: summary
